zcore/__init__.py
zcore/api/__init__.py
zcore/api/app_auth/__init__.py
zcore/api/app_auth/urls.py
zcore/api/app_auth/profile/__init__.py
zcore/api/app_auth/profile/v1/__init__.py
zcore/api/app_auth/profile/v1/serializers.py
zcore/api/app_auth/profile/v1/urls.py
zcore/api/app_auth/profile/v1/utils.py
zcore/api/app_auth/profile/v1/views.py
zcore/api/platform/__init__.py
zcore/api/platform/urls.py
zcore/api/platform/auth/__init__.py
zcore/api/platform/auth/v1/__init__.py
zcore/api/platform/auth/v1/serializers.py
zcore/api/platform/auth/v1/urls.py
zcore/api/platform/auth/v1/views.py
zcore/api/platform/codeassist/__init__.py
zcore/api/platform/codeassist/v1/__init__.py
zcore/api/platform/codeassist/v1/urls.py
zcore/api/platform/codeassist/v1/utils.py
zcore/api/platform/codeassist/v1/views.py
zcore/api/platform/packages/__init__.py
zcore/api/platform/packages/v1/__init__.py
zcore/api/platform/packages/v1/urls.py
zcore/api/platform/packages/v1/views.py
zcore/api/platform/permissions/__init__.py
zcore/api/platform/permissions/v1/__init__.py
zcore/api/platform/permissions/v1/serializers.py
zcore/api/platform/permissions/v1/urls.py
zcore/api/platform/permissions/v1/views.py
zcore/api/platform/tasks/__init__.py
zcore/api/platform/tasks/v1/__init__.py
zcore/api/platform/tasks/v1/serializers.py
zcore/api/platform/tasks/v1/urls.py
zcore/api/platform/tasks/v1/views.py
zcore/api/platform/tenancy/__init__.py
zcore/api/platform/tenancy/v1/__init__.py
zcore/api/platform/tenancy/v1/serializers.py
zcore/api/platform/tenancy/v1/urls.py
zcore/api/platform/tenancy/v1/views.py
zcore/apps/__init__.py
zcore/apps/appauth/__init__.py
zcore/apps/appauth/admin.py
zcore/apps/appauth/apps.py
zcore/apps/appauth/auth_backend.py
zcore/apps/appauth/models.py
zcore/apps/appauth/serializers.py
zcore/apps/appauth/signals.py
zcore/apps/appauth/tests.py
zcore/apps/appauth/urls.py
zcore/apps/appauth/views.py
zcore/apps/appauth/migrations/0001_initial.py
zcorepy-0.2.0rc1.dist-info/LICENSE
zcorepy-0.2.0rc1.dist-info/METADATA
zcorepy-0.2.0rc1.dist-info/WHEEL
zcorepy-0.2.0rc1.dist-info/entry_points.txt
zcorepy-0.2.0rc1.dist-info/top_level.txt
zcorepy-0.2.0rc1.dist-info/RECORD
